babi/__init__.py
babi/__main__.py
babi/buf.py
babi/color.py
babi/color_kd.py
babi/color_manager.py
babi/dim.py
babi/fdict.py
babi/file.py
babi/highlight.py
babi/history.py
babi/horizontal_scrolling.py
babi/linting.py
babi/main.py
babi/perf.py
babi/proc.py
babi/prompt.py
babi/reg.py
babi/screen.py
babi/status.py
babi/textmate_demo.py
babi/theme.py
babi/user_data.py
babi/hl/__init__.py
babi/hl/interface.py
babi/hl/lint_errors.py
babi/hl/replace.py
babi/hl/selection.py
babi/hl/syntax.py
babi/hl/trailing_whitespace.py
babi/linters/__init__.py
babi/linters/flake8.py
babi/linters/pre_commit.py
babi/resources/__init__.py
babi/resources/default_theme.py
babi-1.6.1.dist-info/LICENSE
babi-1.6.1.dist-info/METADATA
babi-1.6.1.dist-info/WHEEL
babi-1.6.1.dist-info/entry_points.txt
babi-1.6.1.dist-info/microsoft_vscode_LICENSE.txt
babi-1.6.1.dist-info/top_level.txt
babi-1.6.1.dist-info/RECORD
