Metadata-Version: 2.1
Name: babi
Version: 1.6.1
Summary: a text editor
Home-page: https://github.com/asottile/babi
Author: Anthony Sottile
Author-email: asottile@umich.edu
License: MIT
Classifier: Programming Language :: Python :: 3
Classifier: Programming Language :: Python :: 3 :: Only
Classifier: Programming Language :: Python :: Implementation :: CPython
Classifier: Programming Language :: Python :: Implementation :: PyPy
Requires-Python: >=3.10
License-File: LICENSE
License-File: licenses/microsoft_vscode_LICENSE.txt
Requires-Dist: babi-grammars
Requires-Dist: identify
Requires-Dist: onigurumacffi>=0.0.18
Requires-Dist: windows-curses>=2.4.0; sys_platform == "win32"
